<?xml version="1.0"?>
<presentation relayVersion="4.4.1">
  <title>d763d8ae49</title>
  <description>Qui aut deserunt perferendis. Enim et recusandae nisi quasi vero. Praesentium quibusdam similique maiores voluptatem consequatur.</description>
  <date>2015-04-08 09:03:16</date>
  <utcDate>2015-04-08 09:03:16</utcDate>
  <profile>PC | Nettbrett | Mobil | Lyd</profile>
  <destinationUrl>http://example.com/relay/ansatt//d763d8ae49</destinationUrl>
  <totalDuration>1690</totalDuration>
  <trimmedDuration>4946</trimmedDuration>
  <startTrimTime>533</startTrimTime>
  <recordedBy>
    <displayName>943bfc1</displayName>
    <email>943bfc11</email>
  </recordedBy>
  <clientInfo>
    <clientIP>83.238.222.121</clientIP>
    <clientComputerName>voluptas</clientComputerName>
  </clientInfo>
  <serverInfo>
    <serverHostname>http://doesnotmatter.example.com</serverHostname>
    <encodingPreset>MP4 with Smart Player (1080p)</encodingPreset>
    <timeToEncode>247</timeToEncode>
    <timeInQueue>844</timeInQueue>
  </serverInfo>
  <sourceRecording>
    <resolution>1920x1080</resolution>
    <fileList>
      <file clientPath="quia" serverPath="error" size="45101" sequence="0" resolution="0x0" duration="0"/>
      <file clientPath="tenetur" serverPath="cum" size="97450" sequence="0" resolution="0x0" duration="0"/>
      <file clientPath="qui" serverPath="nam" size="32997" sequence="0" resolution="0x0" duration="0"/>
    </fileList>
  </sourceRecording>
  <encodeFiles>
    <fileList>
      <file clientPath="tenetur" serverPath="dicta" size="68966" sequence="0" resolution="0x0" duration="0"/>
    </fileList>
  </encodeFiles>
  <outputFiles>
    <fileList>
      <file clientPath="voluptatibus" serverPath="repellat" size="93551" sequence="0" resolution="0x0" duration="0"/>
    </fileList>
  </outputFiles>
</presentation>
